{
  "guilherme.dalbianco": {
    "id": "guilherme.dalbianco",
    "name": "Guilherme Dal Bianco",
    "email": "guilherme.dalbianco@uffs.edu.br"
  },
  "fernando.bevilacqua": {
    "id": "fernando.bevilacqua",
    "name": "Fernando Bevilacqua",
    "email": "fernando.bevilacqua@uffs.edu.br"
  },
  "emilio.wuerges": {
    "id": "emilio.wuerges",
    "name": "Emilio Wuerges",
    "email": "emilio.wuerges@uffs.edu.br"
  },
  "duarte": {
    "id": "duarte",
    "name": "Denio Duarte",
    "email": "duarte@uffs.edu.br"
  },
  "jose.binsfilho": {
    "id": "jose.binsfilho",
    "name": "Jose Carlos Bins Filho",
    "email": "jose.binsfilho@uffs.edu.br"
  },
  "marco.spohn": {
    "id": "marco.spohn",
    "name": "Marco Aurelio Spohn",
    "email": "marco.spohn@uffs.edu.br"
  },
  "claunir.pavan": {
    "id": "claunir.pavan",
    "name": "Claunir Pavan",
    "email": "claunir.pavan@uffs.edu.br"
  },
  "raquel.pegoraro": {
    "id": "raquel.pegoraro",
    "name": "Raquel Aparecida Pegoraro",
    "email": "raquel.pegoraro@uffs.edu.br"
  },
  "padilha": {
    "id": "padilha",
    "name": "Adriano Sanick Padilha",
    "email": "padilha@uffs.edu.br"
  },
  "braulio": {
    "id": "braulio",
    "name": "Braulio Adriano de Mello",
    "email": "braulio@uffs.edu.br"
  },
  "graziela.tonin": {
    "id": "graziela.tonin",
    "name": "Graziela Simone Tonin",
    "email": "graziela.tonin@uffs.edu.br"
  },
  "lcaimi": {
    "id": "lcaimi",
    "name": "Luciano Lores Caimi",
    "email": "lcaimi@uffs.edu.br"
  },
  "asebben": {
    "id": "asebben",
    "name": "Andressa Sebben",
    "email": "asebben@uffs.edu.br"
  },
  "edson.santos": {
    "id": "edson.santos",
    "name": "Edson Ribeiro dos Santos",
    "email": "edson.santos@uffs.edu.br"
  },
  "cf-k": {
    "id": "cf-k",
    "name": "Claudia F. Kratochvil",
    "email": "cf-k@uffs.edu.br"
  },
  "lbordin": {
    "id": "lbordin",
    "name": "Leandro Bordin",
    "email": "lbordin@uffs.edu.br"
  },
  "divane.marcon": {
    "id": "divane.marcon",
    "name": "Divane Marcon",
    "email": "divane.marcon@uffs.edu.br"
  },
  "radin": {
    "id": "radin",
    "name": "Jose Carlos Radin",
    "email": "radin@uffs.edu.br"
  },
  "tatiane.mattei": {
    "id": "tatiane.mattei",
    "name": "Tatiane Salete Mattei",
    "email": "tatiane.mattei@uffs.edu.br"
  },
  "cora": {
    "id": "cora",
    "name": "Elsio Jose Cora",
    "email": "cora@uffs.edu.br"
  },
  "josiane.hoffmann": {
    "id": "josiane.hoffmann",
    "name": "Josiane Marina Hoffmann",
    "email": "josiane.hoffmann@uffs.edu.br"
  },
  "acneri": {
    "id": "acneri",
    "name": "Antonio Marcos Correa Neri",
    "email": "acneri@uffs.edu.br"
  },
  "milton.kist": {
    "id": "milton.kist",
    "name": "Milton Kist",
    "email": "milton.kist@uffs.edu.br"
  },
  "nedilso.brugnera": {
    "id": "nedilso.brugnera",
    "name": "Nedilso Lauro Brugnera",
    "email": "nedilso.brugnera@uffs.edu.br"
  },
  "douglas.balduino": {
    "id": "douglas.balduino",
    "name": "Douglas Balduino Pereira",
    "email": "douglas.balduino@uffs.edu.br"
  },
  "janice": {
    "id": "janice",
    "name": "Janice",
    "email": "janice@uffs.edu.br"
  },
  "glaucio.fontana": {
    "id": "glaucio.fontana",
    "name": "Glaucio",
    "email": "glaucio.fontana@uffs.edu.br"
  },
  "pericles": {
    "id": "pericles",
    "name": "Péricles",
    "email": "pericles@uffs.edu.br"
  },
  "mary.surdi": {
    "id": "mary.surdi",
    "name": "Mary Stela Surdi",
    "email": "mary.surdi@uffs.edu.br"
  },
  "fernando.vojniak": {
    "id": "fernando.vojniak",
    "name": "Fernando Vojniak",
    "email": "fernando.vojniak@uffs.edu.br"
  },
  "isis.matos": {
    "id": "isis.matos",
    "name": "Isis Oliveira Bastos Matos",
    "email": "isis.matos@uffs.edu.br"
  },
  "paulo.bosin": {
    "id": "paulo.bosin",
    "name": "Paulo Bosin",
    "email": "paulo.bosin@uffs.edu.br"
  },
  "ubi.vieira": {
    "id": "ubi.vieira",
    "name": "Ubi Vieira",
    "email": "ubi.vieira@uffs.edu.br"
  },
  "subst.pavan": {
    "id": "subst.pavan",
    "name": "Substituto Pavan",
    "email": "subst.pavan@uffs.edu.br"
  },
  "vaga.zatesko": {
    "id": "vaga.zatesko",
    "name": "Vaga Zatesko",
    "email": "vaga.zatesko@uffs.edu.br"
  }
}
